[{"line":1,"elements":[{"line":3,"name":"","description":"","type":"background","keyword":"Background","steps":[{"name":"url apiURL","result":{"duration":260200,"status":"passed"},"match":{"location":"karate","arguments":[]},"keyword":"*","line":4,"doc_string":{"content_type":"","value":"17:13:15.232 karate.env system property was: null \n","line":4}},{"name":"def DataGenerator = Java.type('helpers.DataGenerator')","result":{"duration":1868400,"status":"passed"},"match":{"location":"karate","arguments":[]},"keyword":"*","line":5}]},{"start_timestamp":"2025-02-13T11:43:15.227Z","line":33,"name":"Test the Create workspace API with -ve scenarios.","description":"","id":"test-the-create-workspace-api-with--ve-scenarios.","type":"scenario","keyword":"Scenario Outline","steps":[{"name":"def randemName = DataGenerator.getRandomWorkSpaceNamename()","result":{"duration":80602300,"status":"passed"},"match":{"location":"karate","arguments":[]},"keyword":"*","line":11},{"name":"path '\/workspaces\/'","result":{"duration":247200,"status":"passed"},"match":{"location":"karate","arguments":[]},"keyword":"Given","line":13},{"name":"headers { 'x-api-key': '#(apiKey)' }","result":{"duration":604100,"status":"passed"},"match":{"location":"karate","arguments":[]},"keyword":"*","line":14},{"name":"request","result":{"duration":192300,"status":"passed"},"match":{"location":"karate","arguments":[]},"keyword":"And","line":15,"doc_string":{"content_type":"","value":"{ \n\"workspace\": {  \n  \"name\": \"\", \n  \"type\": \"personal\", \n  \"description\": \"MYWorkSpaceKarate\", \n  \"visibilityStatus\": \"private\"   \n}   \n}","line":15}},{"name":"method post","result":{"duration":1198496400,"status":"passed"},"match":{"location":"karate","arguments":[]},"keyword":"When","line":26,"doc_string":{"content_type":"","value":"17:13:15.323 request:\n1 > POST https:\/\/api.getpostman.com\/workspaces\n1 > x-api-key: PMAK-67a1fd6a1bd33e0001398b39-8f7df1a19b801ffe2ebdd25b9b6fc3bdfb\n1 > Content-Type: application\/json; charset=UTF-8\n1 > Content-Length: 106\n1 > Host: api.getpostman.com\n1 > Connection: Keep-Alive\n1 > User-Agent: Apache-HttpClient\/4.5.14 (Java\/17.0.10)\n1 > Accept-Encoding: gzip,deflate\n{\"workspace\":{\"name\":\"\",\"type\":\"personal\",\"description\":\"MYWorkSpaceKarate\",\"visibilityStatus\":\"private\"}}\n\n17:13:16.515 response time in milliseconds: 1191\n1 < 400\n1 < Date: Thu, 13 Feb 2025 11:43:15 GMT\n1 < Content-Type: application\/json; charset=utf-8\n1 < Content-Length: 100\n1 < Connection: keep-alive\n1 < Server: nginx\n1 < x-frame-options: deny\n1 < x-xss-protection: 1; mode=block\n1 < x-content-type-options: nosniff\n1 < referrer-policy: no-referrer-when-downgrade\n1 < access-control-allow-origin: *\n1 < access-control-allow-methods: GET,POST,PUT,DELETE\n1 < access-control-allow-headers: content-type,x-api-key\n1 < access-control-allow-credentials: false\n1 < x-ratelimit-limit: 300\n1 < x-ratelimit-reset: 55\n1 < x-ratelimit-remaining: 286\n1 < ratelimit: limit=300, remaining=286, reset=55\n1 < ratelimit-policy: 300;w=60\n1 < ratelimit-limit: 300\n1 < ratelimit-remaining: 286\n1 < ratelimit-reset: 55\n1 < ratelimit-limit-month: 10000\n1 < ratelimit-remaining-month: 7180\n1 < x-ratelimit-limit-month: 10000\n1 < x-ratelimit-remaining-month: 7180\n1 < uWebSockets: 20\n{\"error\":{\"name\":\"invalidParamError\",\"message\":\"body.name should NOT be shorter than 1 characters\"}}\n\n","line":26}},{"name":"status 400","result":{"duration":20300,"status":"passed"},"match":{"location":"karate","arguments":[]},"keyword":"Then","line":27},{"name":"match response == {\"error\": {\"name\": \"invalidParamError\", \"message\": \"body.name should NOT be shorter than 1 characters\"}}","result":{"duration":3924500,"status":"passed"},"match":{"location":"karate","arguments":[]},"keyword":"And","line":28}],"tags":[]},{"line":3,"name":"","description":"","type":"background","keyword":"Background","steps":[{"name":"url apiURL","result":{"duration":193700,"status":"passed"},"match":{"location":"karate","arguments":[]},"keyword":"*","line":4,"doc_string":{"content_type":"","value":"17:13:15.454 karate.env system property was: null \n","line":4}},{"name":"def DataGenerator = Java.type('helpers.DataGenerator')","result":{"duration":1647100,"status":"passed"},"match":{"location":"karate","arguments":[]},"keyword":"*","line":5}]},{"start_timestamp":"2025-02-13T11:43:15.449Z","line":34,"name":"Test the Create workspace API with -ve scenarios.","description":"","id":"test-the-create-workspace-api-with--ve-scenarios.","type":"scenario","keyword":"Scenario Outline","steps":[{"name":"def randemName = DataGenerator.getRandomWorkSpaceNamename()","result":{"duration":70405200,"status":"passed"},"match":{"location":"karate","arguments":[]},"keyword":"*","line":11},{"name":"path '\/workspaces\/'","result":{"duration":1726100,"status":"passed"},"match":{"location":"karate","arguments":[]},"keyword":"Given","line":13},{"name":"headers { 'x-api-key': '#(apiKey)' }","result":{"duration":4574400,"status":"passed"},"match":{"location":"karate","arguments":[]},"keyword":"*","line":14},{"name":"request","result":{"duration":2266000,"status":"passed"},"match":{"location":"karate","arguments":[]},"keyword":"And","line":15,"doc_string":{"content_type":"","value":"{ \n\"workspace\": {  \n  \"name\": \"AnotherWorkSpace\", \n  \"type\": \"test\", \n  \"description\": \"AnotherDescription\", \n  \"visibilityStatus\": \"private\"   \n}   \n}","line":15}},{"name":"method post","result":{"duration":1001906200,"status":"passed"},"match":{"location":"karate","arguments":[]},"keyword":"When","line":26,"doc_string":{"content_type":"","value":"17:13:15.545 request:\n1 > POST https:\/\/api.getpostman.com\/workspaces\n1 > x-api-key: PMAK-67a1fd6a1bd33e0001398b39-8f7df1a19b801ffe2ebdd25b9b6fc3bdfb\n1 > Content-Type: application\/json; charset=UTF-8\n1 > Content-Length: 119\n1 > Host: api.getpostman.com\n1 > Connection: Keep-Alive\n1 > User-Agent: Apache-HttpClient\/4.5.14 (Java\/17.0.10)\n1 > Accept-Encoding: gzip,deflate\n{\"workspace\":{\"name\":\"AnotherWorkSpace\",\"type\":\"test\",\"description\":\"AnotherDescription\",\"visibilityStatus\":\"private\"}}\n\n17:13:16.541 response time in milliseconds: 994\n1 < 400\n1 < Date: Thu, 13 Feb 2025 11:43:15 GMT\n1 < Content-Type: application\/json; charset=utf-8\n1 < Content-Length: 117\n1 < Connection: keep-alive\n1 < Server: nginx\n1 < x-frame-options: deny\n1 < x-xss-protection: 1; mode=block\n1 < x-content-type-options: nosniff\n1 < referrer-policy: no-referrer-when-downgrade\n1 < access-control-allow-origin: *\n1 < access-control-allow-methods: GET,POST,PUT,DELETE\n1 < access-control-allow-headers: content-type,x-api-key\n1 < access-control-allow-credentials: false\n1 < x-ratelimit-limit: 300\n1 < x-ratelimit-reset: 55\n1 < x-ratelimit-remaining: 285\n1 < ratelimit: limit=300, remaining=285, reset=55\n1 < ratelimit-policy: 300;w=60\n1 < ratelimit-limit: 300\n1 < ratelimit-remaining: 285\n1 < ratelimit-reset: 55\n1 < ratelimit-limit-month: 10000\n1 < ratelimit-remaining-month: 7179\n1 < x-ratelimit-limit-month: 10000\n1 < x-ratelimit-remaining-month: 7179\n1 < uWebSockets: 20\n{\"error\":{\"name\":\"invalidParamError\",\"message\":\"body.visibilityStatus should be equal to one of the allowed values\"}}\n\n","line":26}},{"name":"status 400","result":{"duration":3871500,"status":"passed"},"match":{"location":"karate","arguments":[]},"keyword":"Then","line":27},{"name":"match response == {\"error\": {\"name\": \"invalidParamError\", \"message\": \"body.visibilityStatus should be equal to one of the allowed values\"}}","result":{"duration":1300600,"status":"passed"},"match":{"location":"karate","arguments":[]},"keyword":"And","line":28}],"tags":[]},{"line":3,"name":"","description":"","type":"background","keyword":"Background","steps":[{"name":"url apiURL","result":{"duration":208300,"status":"passed"},"match":{"location":"karate","arguments":[]},"keyword":"*","line":4,"doc_string":{"content_type":"","value":"17:13:15.687 karate.env system property was: null \n","line":4}},{"name":"def DataGenerator = Java.type('helpers.DataGenerator')","result":{"duration":1665700,"status":"passed"},"match":{"location":"karate","arguments":[]},"keyword":"*","line":5}]},{"start_timestamp":"2025-02-13T11:43:15.683Z","line":35,"name":"Test the Create workspace API with -ve scenarios.","description":"","id":"test-the-create-workspace-api-with--ve-scenarios.","type":"scenario","keyword":"Scenario Outline","steps":[{"name":"def randemName = DataGenerator.getRandomWorkSpaceNamename()","result":{"duration":68293700,"status":"passed"},"match":{"location":"karate","arguments":[]},"keyword":"*","line":11},{"name":"path '\/workspaces\/'","result":{"duration":1109400,"status":"passed"},"match":{"location":"karate","arguments":[]},"keyword":"Given","line":13},{"name":"headers { 'x-api-key': '#(apiKey)' }","result":{"duration":769000,"status":"passed"},"match":{"location":"karate","arguments":[]},"keyword":"*","line":14},{"name":"request","result":{"duration":316800,"status":"passed"},"match":{"location":"karate","arguments":[]},"keyword":"And","line":15,"doc_string":{"content_type":"","value":"{ \n\"workspace\": {  \n  \"name\": \"AnotherWorkSpace\", \n  \"type\": \"test\", \n  \"description\": \"AnotherDescription\", \n  \"visibilityStatus\": \"private\"   \n}   \n}","line":15}},{"name":"method post","result":{"duration":922599900,"status":"passed"},"match":{"location":"karate","arguments":[]},"keyword":"When","line":26,"doc_string":{"content_type":"","value":"17:13:15.767 request:\n1 > POST https:\/\/api.getpostman.com\/workspaces\n1 > x-api-key: PMAK-67a1fd6a1bd33e0001398b39-8f7df1a19b801ffe2ebdd25b9b6fc3bdfb\n1 > Content-Type: application\/json; charset=UTF-8\n1 > Content-Length: 119\n1 > Host: api.getpostman.com\n1 > Connection: Keep-Alive\n1 > User-Agent: Apache-HttpClient\/4.5.14 (Java\/17.0.10)\n1 > Accept-Encoding: gzip,deflate\n{\"workspace\":{\"name\":\"AnotherWorkSpace\",\"type\":\"test\",\"description\":\"AnotherDescription\",\"visibilityStatus\":\"private\"}}\n\n17:13:16.686 response time in milliseconds: 916\n1 < 400\n1 < Date: Thu, 13 Feb 2025 11:43:16 GMT\n1 < Content-Type: application\/json; charset=utf-8\n1 < Content-Length: 117\n1 < Connection: keep-alive\n1 < Server: nginx\n1 < x-frame-options: deny\n1 < x-xss-protection: 1; mode=block\n1 < x-content-type-options: nosniff\n1 < referrer-policy: no-referrer-when-downgrade\n1 < access-control-allow-origin: *\n1 < access-control-allow-methods: GET,POST,PUT,DELETE\n1 < access-control-allow-headers: content-type,x-api-key\n1 < access-control-allow-credentials: false\n1 < x-ratelimit-limit: 300\n1 < x-ratelimit-reset: 54\n1 < x-ratelimit-remaining: 284\n1 < ratelimit: limit=300, remaining=284, reset=54\n1 < ratelimit-policy: 300;w=60\n1 < ratelimit-limit: 300\n1 < ratelimit-remaining: 284\n1 < ratelimit-reset: 54\n1 < ratelimit-limit-month: 10000\n1 < ratelimit-remaining-month: 7178\n1 < x-ratelimit-limit-month: 10000\n1 < x-ratelimit-remaining-month: 7178\n1 < uWebSockets: 20\n{\"error\":{\"name\":\"invalidParamError\",\"message\":\"body.visibilityStatus should be equal to one of the allowed values\"}}\n\n","line":26}},{"name":"status 400","result":{"duration":54300,"status":"passed"},"match":{"location":"karate","arguments":[]},"keyword":"Then","line":27},{"name":"match response == {\"error\": {\"name\": \"invalidParamError\", \"message\": \"body.visibilityStatus should be equal to one of the allowed values\"}}","result":{"duration":1027400,"status":"passed"},"match":{"location":"karate","arguments":[]},"keyword":"And","line":28}],"tags":[]},{"line":3,"name":"","description":"","type":"background","keyword":"Background","steps":[{"name":"url apiURL","result":{"duration":536900,"status":"passed"},"match":{"location":"karate","arguments":[]},"keyword":"*","line":4,"doc_string":{"content_type":"","value":"17:13:16.016 karate.env system property was: null \n","line":4}},{"name":"def DataGenerator = Java.type('helpers.DataGenerator')","result":{"duration":3481800,"status":"passed"},"match":{"location":"karate","arguments":[]},"keyword":"*","line":5}]},{"start_timestamp":"2025-02-13T11:43:16.011Z","line":36,"name":"Test the Create workspace API with -ve scenarios.","description":"","id":"test-the-create-workspace-api-with--ve-scenarios.","type":"scenario","keyword":"Scenario Outline","steps":[{"name":"def randemName = DataGenerator.getRandomWorkSpaceNamename()","result":{"duration":149189700,"status":"passed"},"match":{"location":"karate","arguments":[]},"keyword":"*","line":11},{"name":"path '\/workspaces\/'","result":{"duration":1217400,"status":"passed"},"match":{"location":"karate","arguments":[]},"keyword":"Given","line":13},{"name":"headers { 'x-api-key': '#(apiKey)' }","result":{"duration":1544100,"status":"passed"},"match":{"location":"karate","arguments":[]},"keyword":"*","line":14},{"name":"request","result":{"duration":247100,"status":"passed"},"match":{"location":"karate","arguments":[]},"keyword":"And","line":15,"doc_string":{"content_type":"","value":"{ \n\"workspace\": {  \n  \"name\": \"AnotherWorkSpace\", \n  \"type\": \"test\", \n  \"description\": \"AnotherDescription\", \n  \"visibilityStatus\": \"private\"   \n}   \n}","line":15}},{"name":"method post","result":{"duration":957333700,"status":"passed"},"match":{"location":"karate","arguments":[]},"keyword":"When","line":26,"doc_string":{"content_type":"","value":"17:13:16.194 request:\n1 > POST https:\/\/api.getpostman.com\/workspaces\n1 > x-api-key: PMAK-67a1fd6a1bd33e0001398b39-8f7df1a19b801ffe2ebdd25b9b6fc3bdfb\n1 > Content-Type: application\/json; charset=UTF-8\n1 > Content-Length: 119\n1 > Host: api.getpostman.com\n1 > Connection: Keep-Alive\n1 > User-Agent: Apache-HttpClient\/4.5.14 (Java\/17.0.10)\n1 > Accept-Encoding: gzip,deflate\n{\"workspace\":{\"name\":\"AnotherWorkSpace\",\"type\":\"test\",\"description\":\"AnotherDescription\",\"visibilityStatus\":\"private\"}}\n\n17:13:17.139 response time in milliseconds: 944\n1 < 400\n1 < Date: Thu, 13 Feb 2025 11:43:16 GMT\n1 < Content-Type: application\/json; charset=utf-8\n1 < Content-Length: 117\n1 < Connection: keep-alive\n1 < Server: nginx\n1 < x-frame-options: deny\n1 < x-xss-protection: 1; mode=block\n1 < x-content-type-options: nosniff\n1 < referrer-policy: no-referrer-when-downgrade\n1 < access-control-allow-origin: *\n1 < access-control-allow-methods: GET,POST,PUT,DELETE\n1 < access-control-allow-headers: content-type,x-api-key\n1 < access-control-allow-credentials: false\n1 < x-ratelimit-limit: 300\n1 < x-ratelimit-reset: 54\n1 < x-ratelimit-remaining: 283\n1 < ratelimit: limit=300, remaining=283, reset=54\n1 < ratelimit-policy: 300;w=60\n1 < ratelimit-limit: 300\n1 < ratelimit-remaining: 283\n1 < ratelimit-reset: 54\n1 < ratelimit-limit-month: 10000\n1 < ratelimit-remaining-month: 7177\n1 < x-ratelimit-limit-month: 10000\n1 < x-ratelimit-remaining-month: 7177\n1 < uWebSockets: 20\n{\"error\":{\"name\":\"invalidParamError\",\"message\":\"body.visibilityStatus should be equal to one of the allowed values\"}}\n\n","line":26}},{"name":"status 400","result":{"duration":8300,"status":"passed"},"match":{"location":"karate","arguments":[]},"keyword":"Then","line":27},{"name":"match response == {\"error\": {\"name\": \"invalidParamError\", \"message\": \"body.visibilityStatus should be equal to one of the allowed values\"}}","result":{"duration":403500,"status":"passed"},"match":{"location":"karate","arguments":[]},"keyword":"And","line":28}],"tags":[]},{"line":3,"name":"","description":"","type":"background","keyword":"Background","steps":[{"name":"url apiURL","result":{"duration":435300,"status":"passed"},"match":{"location":"karate","arguments":[]},"keyword":"*","line":4,"doc_string":{"content_type":"","value":"17:13:16.532 karate.env system property was: null \n","line":4}},{"name":"def DataGenerator = Java.type('helpers.DataGenerator')","result":{"duration":2636700,"status":"passed"},"match":{"location":"karate","arguments":[]},"keyword":"*","line":5}]},{"start_timestamp":"2025-02-13T11:43:16.526Z","line":37,"name":"Test the Create workspace API with -ve scenarios.","description":"","id":"test-the-create-workspace-api-with--ve-scenarios.","type":"scenario","keyword":"Scenario Outline","steps":[{"name":"def randemName = DataGenerator.getRandomWorkSpaceNamename()","result":{"duration":68431400,"status":"passed"},"match":{"location":"karate","arguments":[]},"keyword":"*","line":11},{"name":"path '\/workspaces\/'","result":{"duration":2405200,"status":"passed"},"match":{"location":"karate","arguments":[]},"keyword":"Given","line":13},{"name":"headers { 'x-api-key': '#(apiKey)' }","result":{"duration":3626200,"status":"passed"},"match":{"location":"karate","arguments":[]},"keyword":"*","line":14},{"name":"request","result":{"duration":1243100,"status":"passed"},"match":{"location":"karate","arguments":[]},"keyword":"And","line":15,"doc_string":{"content_type":"","value":"{ \n\"workspace\": {  \n  \"name\": \"AnotherWorkSpace\", \n  \"type\": \"test\", \n  \"description\": \"AnotherDescription\", \n  \"visibilityStatus\": \"private\"   \n}   \n}","line":15}},{"name":"method post","result":{"duration":995764800,"status":"passed"},"match":{"location":"karate","arguments":[]},"keyword":"When","line":26,"doc_string":{"content_type":"","value":"17:13:16.620 request:\n1 > POST https:\/\/api.getpostman.com\/workspaces\n1 > x-api-key: PMAK-67a1fd6a1bd33e0001398b39-8f7df1a19b801ffe2ebdd25b9b6fc3bdfb\n1 > Content-Type: application\/json; charset=UTF-8\n1 > Content-Length: 119\n1 > Host: api.getpostman.com\n1 > Connection: Keep-Alive\n1 > User-Agent: Apache-HttpClient\/4.5.14 (Java\/17.0.10)\n1 > Accept-Encoding: gzip,deflate\n{\"workspace\":{\"name\":\"AnotherWorkSpace\",\"type\":\"test\",\"description\":\"AnotherDescription\",\"visibilityStatus\":\"private\"}}\n\n17:13:17.610 response time in milliseconds: 988\n1 < 400\n1 < Date: Thu, 13 Feb 2025 11:43:17 GMT\n1 < Content-Type: application\/json; charset=utf-8\n1 < Content-Length: 117\n1 < Connection: keep-alive\n1 < Server: nginx\n1 < x-frame-options: deny\n1 < x-xss-protection: 1; mode=block\n1 < x-content-type-options: nosniff\n1 < referrer-policy: no-referrer-when-downgrade\n1 < access-control-allow-origin: *\n1 < access-control-allow-methods: GET,POST,PUT,DELETE\n1 < access-control-allow-headers: content-type,x-api-key\n1 < access-control-allow-credentials: false\n1 < x-ratelimit-limit: 300\n1 < x-ratelimit-reset: 54\n1 < x-ratelimit-remaining: 282\n1 < ratelimit: limit=300, remaining=282, reset=54\n1 < ratelimit-policy: 300;w=60\n1 < ratelimit-limit: 300\n1 < ratelimit-remaining: 282\n1 < ratelimit-reset: 54\n1 < ratelimit-limit-month: 10000\n1 < ratelimit-remaining-month: 7176\n1 < x-ratelimit-limit-month: 10000\n1 < x-ratelimit-remaining-month: 7176\n1 < uWebSockets: 20\n{\"error\":{\"name\":\"invalidParamError\",\"message\":\"body.visibilityStatus should be equal to one of the allowed values\"}}\n\n","line":26}},{"name":"status 400","result":{"duration":8100,"status":"passed"},"match":{"location":"karate","arguments":[]},"keyword":"Then","line":27},{"name":"match response == {\"error\": {\"name\": \"invalidParamError\", \"message\": \"body.visibilityStatus should be equal to one of the allowed values\"}}","result":{"duration":430000,"status":"passed"},"match":{"location":"karate","arguments":[]},"keyword":"And","line":28}],"tags":[]}],"name":"PostmanAPI\/APITEST\/WorkSpaceFeature\/TestCreateWorkSpaceWithDiffData.feature","description":"Workspace Management.","id":"workspace-management.","keyword":"Feature","uri":"PostmanAPI\/APITEST\/WorkSpaceFeature\/TestCreateWorkSpaceWithDiffData.feature"}]